optimum/commands/env.py
optimum/nvidia/__init__.py
optimum/nvidia/errors.py
optimum/nvidia/hub.py
optimum/nvidia/logging.py
optimum/nvidia/runtime.py
optimum/nvidia/version.py
optimum/nvidia/compression/__init__.py
optimum/nvidia/compression/modelopt.py
optimum/nvidia/export/__init__.py
optimum/nvidia/export/cli.py
optimum/nvidia/export/config.py
optimum/nvidia/export/converter.py
optimum/nvidia/export/workspace.py
optimum/nvidia/generation/logits_process.py
optimum/nvidia/lang/__init__.py
optimum/nvidia/models/__init__.py
optimum/nvidia/models/auto.py
optimum/nvidia/models/base.py
optimum/nvidia/models/gemma.py
optimum/nvidia/models/llama.py
optimum/nvidia/models/mistral.py
optimum/nvidia/models/mixtral.py
optimum/nvidia/models/whisper.py
optimum/nvidia/pipelines/__init__.py
optimum/nvidia/pipelines/base.py
optimum/nvidia/pipelines/text_generation.py
optimum/nvidia/subpackage/__init__.py
optimum/nvidia/subpackage/commands/__init__.py
optimum/nvidia/subpackage/commands/env.py
optimum/nvidia/subpackage/commands/export.py
optimum/nvidia/utils/__init__.py
optimum/nvidia/utils/cli.py
optimum/nvidia/utils/constants.py
optimum/nvidia/utils/env.py
optimum/nvidia/utils/hub.py
optimum/nvidia/utils/import_utils.py
optimum/nvidia/utils/nvml.py
optimum/nvidia/utils/offload.py
optimum/nvidia/utils/onnx.py
optimum/nvidia/utils/patching.py
optimum/nvidia/utils/tests/__init__.py
optimum/nvidia/utils/tests/assertions.py
optimum/nvidia/utils/tests/utils.py
optimum_nvidia-0.1.0b9.dist-info/LICENSE
optimum_nvidia-0.1.0b9.dist-info/METADATA
optimum_nvidia-0.1.0b9.dist-info/WHEEL
optimum_nvidia-0.1.0b9.dist-info/dependency_links.txt
optimum_nvidia-0.1.0b9.dist-info/entry_points.txt
optimum_nvidia-0.1.0b9.dist-info/top_level.txt
optimum_nvidia-0.1.0b9.dist-info/RECORD
