Metadata-Version: 2.2
Name: optimum-nvidia
Version: 0.1.0b9
Summary: Optimum Nvidia is the interface between the Hugging Face Transformers and NVIDIA GPUs. "
Home-page: https://huggingface.co/hardware/nvidia
Author: HuggingFace Inc. Machine Learning Optimization Team
Author-email: "HuggingFace Inc. Machine Learning Optimization Team" <hardware@huggingface.co>
License: Apache/2.0
Project-URL: Homepage, https://huggingface.co/hardware/nvidia
Project-URL: Repository, https://github.com/huggingface/optimum-nvidia
Project-URL: Issues, https://github.com/huggingface/optimum-nvidia/issues
Keywords: transformers,neural-network,inference,nvidia,tensorrt,ampere,hopper
Classifier: Development Status :: 2 - Pre-Alpha
Classifier: License :: OSI Approved :: Apache Software License
Classifier: Intended Audience :: Developers
Classifier: Intended Audience :: Education
Classifier: Intended Audience :: Science/Research
Classifier: Operating System :: OS Independent
Classifier: Programming Language :: Python :: 3.10
Classifier: Topic :: Scientific/Engineering :: Artificial Intelligence
Requires-Python: >=3.10
License-File: LICENSE
Requires-Dist: accelerate>=0.26
Requires-Dist: datasets>=2.14.0
Requires-Dist: huggingface-hub>=0.24.0
Requires-Dist: hf-transfer==0.1.6
Requires-Dist: mpi4py<4.0.0
Requires-Dist: mpmath==1.3.0
Requires-Dist: numpy<2.0.0,>=1.26.0
Requires-Dist: onnx>=1.17.0
Requires-Dist: optimum>=1.21.0
Requires-Dist: setuptools
Requires-Dist: tensorrt-llm==0.16.0
Requires-Dist: torch<=2.6.0a,>=2.4.0a
Requires-Dist: transformers>=4.45.1
Requires-Dist: pynvml
Provides-Extra: tests
Requires-Dist: mock; extra == "tests"
Requires-Dist: pytest; extra == "tests"
Requires-Dist: pytest-console-scripts; extra == "tests"
Requires-Dist: pytest-xdist; extra == "tests"
Requires-Dist: psutil; extra == "tests"
Requires-Dist: parameterized; extra == "tests"
Dynamic: author
Dynamic: home-page
